amazon_braket_algorithm_library-1.7.0.dist-info/licenses/LICENSE
amazon_braket_algorithm_library-1.7.0.dist-info/licenses/NOTICE
braket/_algos/_version.py
braket/experimental/__init__.py
braket/experimental/algorithms/__init__.py
braket/experimental/algorithms/adaptive_shot_allocation/__init__.py
braket/experimental/algorithms/adaptive_shot_allocation/adaptive_allocator.py
braket/experimental/algorithms/adaptive_shot_allocation/adaptive_allocator_braket_helpers.py
braket/experimental/algorithms/bells_inequality/__init__.py
braket/experimental/algorithms/bells_inequality/bells_inequality.py
braket/experimental/algorithms/bernstein_vazirani/__init__.py
braket/experimental/algorithms/bernstein_vazirani/bernstein_vazirani.py
braket/experimental/algorithms/chsh_inequality/__init__.py
braket/experimental/algorithms/chsh_inequality/chsh_inequality.py
braket/experimental/algorithms/deutsch_jozsa/__init__.py
braket/experimental/algorithms/deutsch_jozsa/deutsch_jozsa.py
braket/experimental/algorithms/grovers_search/__init__.py
braket/experimental/algorithms/grovers_search/grovers_search.py
braket/experimental/algorithms/qc_qmc/__init__.py
braket/experimental/algorithms/qc_qmc/classical_qmc.py
braket/experimental/algorithms/qc_qmc/qc_qmc.py
braket/experimental/algorithms/quantum_approximate_optimization/__init__.py
braket/experimental/algorithms/quantum_approximate_optimization/quantum_approximate_optimization.py
braket/experimental/algorithms/quantum_circuit_born_machine/__init__.py
braket/experimental/algorithms/quantum_circuit_born_machine/qcbm.py
braket/experimental/algorithms/quantum_fourier_transform/__init__.py
braket/experimental/algorithms/quantum_fourier_transform/quantum_fourier_transform.py
braket/experimental/algorithms/quantum_phase_estimation/__init__.py
braket/experimental/algorithms/quantum_phase_estimation/quantum_phase_estimation.py
braket/experimental/algorithms/quantum_walk/__init__.py
braket/experimental/algorithms/quantum_walk/quantum_walk.py
braket/experimental/algorithms/shors/__init__.py
braket/experimental/algorithms/shors/shors.py
amazon_braket_algorithm_library-1.7.0.dist-info/METADATA
amazon_braket_algorithm_library-1.7.0.dist-info/WHEEL
amazon_braket_algorithm_library-1.7.0.dist-info/top_level.txt
amazon_braket_algorithm_library-1.7.0.dist-info/RECORD
