Metadata-Version: 2.4
Name: amazon-braket-algorithm-library
Version: 1.7.0
Summary: An open source library of quantum computing algorithms implemented on Amazon Braket
Home-page: https://github.com/amazon-braket/amazon-braket-algorithm-library
Author: Amazon Web Services
License: Apache License 2.0
Keywords: Amazon AWS Quantum
Classifier: Intended Audience :: Developers
Classifier: Natural Language :: English
Classifier: License :: OSI Approved :: Apache Software License
Classifier: Programming Language :: Python
Classifier: Programming Language :: Python :: 3.11
Classifier: Programming Language :: Python :: 3.12
Classifier: Programming Language :: Python :: 3.13
Requires-Python: >= 3.11
License-File: LICENSE
License-File: NOTICE
Requires-Dist: amazon-braket-sdk>=1.35.1
Requires-Dist: numpy
Requires-Dist: openfermion>=1.5.1
Requires-Dist: pennylane>=0.34.0
Requires-Dist: scipy>=1.5.2
Requires-Dist: sympy<1.13
Provides-Extra: test
Requires-Dist: pytest; extra == "test"
Requires-Dist: pytest-cov; extra == "test"
Requires-Dist: pytest-rerunfailures; extra == "test"
Requires-Dist: pytest-xdist; extra == "test"
Requires-Dist: ruff; extra == "test"
Requires-Dist: sphinx; extra == "test"
Requires-Dist: sphinx-rtd-theme; extra == "test"
Requires-Dist: sphinxcontrib-apidoc; extra == "test"
Requires-Dist: tox; extra == "test"
Dynamic: author
Dynamic: classifier
Dynamic: description
Dynamic: description-content-type
Dynamic: home-page
Dynamic: keywords
Dynamic: license
Dynamic: license-file
Dynamic: provides-extra
Dynamic: requires-dist
Dynamic: requires-python
Dynamic: summary
